MANIFEST.in
requirements.txt
setup.cfg
setup.py
versioneer.py
barnes_hut_tsne.egg-info/PKG-INFO
barnes_hut_tsne.egg-info/SOURCES.txt
barnes_hut_tsne.egg-info/dependency_links.txt
barnes_hut_tsne.egg-info/requires.txt
barnes_hut_tsne.egg-info/top_level.txt
tsne/__init__.py
tsne/_version.py
tsne/bh_sne.pyx
tsne/bh_sne_src/Readme.txt
tsne/bh_sne_src/compile_linux
tsne/bh_sne_src/compile_mac
tsne/bh_sne_src/fast_tsne.m
tsne/bh_sne_src/quadtree.cpp
tsne/bh_sne_src/quadtree.h
tsne/bh_sne_src/tsne.cpp
tsne/bh_sne_src/tsne.h
tsne/bh_sne_src/vptree.h
tsne/tests/__init__.py
tsne/tests/test_iris.py
tsne/tests/test_seed.py