Metadata-Version: 1.0
Name: barnes-hut-tsne
Version: 0.2.0
Summary: TSNE implementations for python
Home-page: https://github.com/rspeer/barnes-hut-tsne
Author: Rob Speer
Author-email: rob@luminoso.com
License: Apache License Version 2.0, January 2004
Platform: UNKNOWN
